nidmfsl/__init__.py
nidmfsl/fsl_exporter/__init__.py
nidmfsl/fsl_exporter/fsl_exporter.py
nidmfsl/fsl_exporter/objects/__init__.py
nidmfsl/fsl_exporter/objects/fsl_objects.py
nidmfsl-2.2.0.data/scripts/nidmfsl
nidmfsl-2.2.0.dist-info/METADATA
nidmfsl-2.2.0.dist-info/RECORD
nidmfsl-2.2.0.dist-info/WHEEL
nidmfsl-2.2.0.dist-info/top_level.txt
test/__init__.py
test/export_test_battery.py
test/test_fsl_export.py
test/test_install.py
