Metadata-Version: 2.1
Name: nidmfsl
Version: 2.2.0
Summary: Export of FSL statistical results using NIDM as specified at http://nidm.nidash.org/specs/nidm-results.html.
Home-page: UNKNOWN
Author: Camille Maumet
Author-email: c.m.j.maumet@warwick.ac.uk
License: BSD
Keywords: Prov,NIDM,Provenance
Platform: UNKNOWN
Classifier: Development Status :: 3 - Alpha
Classifier: Topic :: Utilities
Classifier: License :: OSI Approved :: MIT License
Classifier: Programming Language :: Python :: 3
Requires-Dist: nidmresults (<3.0.0,>=2.1.0)
Requires-Dist: scipy
